gptdriver_client/__init__.py
gptdriver_client/gpt_driver.py
gptdriver_client/gpt_driver_core.py
gptdriver_client/helpers.py
gptdriver_client/logging_config.py
gptdriver_client/requests_handler.py
gptdriver_client/stability_detector.py
gptdriver_client/types.py
gptdriver_client-2.1.2.dist-info/licenses/LICENSE
gptdriver_client-2.1.2.dist-info/METADATA
gptdriver_client-2.1.2.dist-info/WHEEL
gptdriver_client-2.1.2.dist-info/top_level.txt
gptdriver_client-2.1.2.dist-info/RECORD
