Metadata-Version: 2.4
Name: gptdriver-client
Version: 2.1.2
Summary: Test your mobile apps with the AI native GPT Driver.
Author-email: MobileBoost <chris@mobileboost.io>
Project-URL: Homepage, https://www.mobileboost.io
Classifier: Programming Language :: Python :: 3
Classifier: License :: OSI Approved :: GNU Affero General Public License v3 or later (AGPLv3+)
Classifier: Operating System :: OS Independent
Requires-Python: >=3.9
License-File: LICENSE
Requires-Dist: requests
Requires-Dist: pydantic
Requires-Dist: Appium-Python-Client
Requires-Dist: pillow
Dynamic: license-file
